tcflow/EMD_MD_OPs.py
tcflow/EMD_reprocess_OPs.py
tcflow/EMD_run.py
tcflow/NEMD_MD_OPs.py
tcflow/NEMD_reprocess_OPs.py
tcflow/NEMD_run.py
tcflow/__init__.py
tcflow/input_gen.py
tcflow/submit.py
tcflow-0.1.3.dist-info/LICENSE
tcflow-0.1.3.dist-info/METADATA
tcflow-0.1.3.dist-info/WHEEL
tcflow-0.1.3.dist-info/entry_points.txt
tcflow-0.1.3.dist-info/top_level.txt
tcflow-0.1.3.dist-info/RECORD
